README.rst
setup.py
poco/__init__.py
poco0.egg-info/PKG-INFO
poco0.egg-info/SOURCES.txt
poco0.egg-info/dependency_links.txt
poco0.egg-info/top_level.txt