Metadata-Version: 1.0
Name: poco0
Version: 1.0.5
Summary: Poco cross-engine UI automated test framework.
Home-page: UNKNOWN
Author: adolli
Author-email: adolli@163.com
License: Apache License 2.0
Keywords: poco
Platform: UNKNOWN
